shadowsight/__init__.py
shadowsight/conf_sample.py
shadowsight/config.py
shadowsight/monitoring.py
shadowsight/publish.py
shadowsight/shadow.py
shadowsight/utils.py
shadowsight-1.0.3.dist-info/METADATA
shadowsight-1.0.3.dist-info/WHEEL
shadowsight-1.0.3.dist-info/entry_points.txt
shadowsight-1.0.3.dist-info/RECORD
